{
  "videos": [
    {
      "id": 1,
      "title": "Boom: The Future of Supersonic Flight?",
      "description": "Thank you to my patreon supporters: Adam Flohr, darth patron, Zoltan Gramantik, Josh Levent, Henning Basma, Karl Andersson, Mark Govea, Mershal Alshammari, Hank Green, Tony Kuchta, Sam Stockdale, Jason A. Diegmueller, Chris Plays Games, Peter Hogan-De Paul, William Leu, Frejden Jarrett, Vincent Mooney & Ian Dundore",
      "image": "flight.jpg",
      "video": "supersonic-flight.mp4"
    },
    {
      "id": 2,
      "title": "Game Boy",
      "description": "A video about the original handheld console.",
      "image": "gameboy.jpg",
      "video": "original-gameboy.mp4"
    },
    {
      "id": 3,
      "title": "Game Boy Pocket",
      "description": "A video about the revised console.",
      "image": "gameboy-pocket.jpg",
      "video": "gameboy-pocket.mp4"
    },
    {
      "id": 4,
      "title": "Nintendo Game Boy Color Unboxing!",
      "description": "A video about the color revision.",
      "image": "gameboy-color.jpg",
      "video": "gbc.mp4"
    }
  ]
}